[{"name":"Flower Rangoli # Peacock Rangoli","image":"https://i.ytimg.com/vi/Y9elOLXRHn8/mqdefault.jpg","URL":"https://youtu.be/Y9elOLXRHn8","youtubeID":"Y9elOLXRHn8","source":"Rangoli Arts & Salad Decorations"},{"name":"Onam Pookalam","image":"https://i.ytimg.com/vi/OXm5BcxnjnI/mqdefault.jpg","URL":"https://youtu.be/OXm5BcxnjnI","youtubeID":"OXm5BcxnjnI","source":"Friday Magazine"},{"name":"simple onam atha pookalam","image":"https://i.ytimg.com/vi/AmNPprbICPQ/mqdefault.jpg","URL":"https://youtu.be/AmNPprbICPQ","youtubeID":"AmNPprbICPQ","source":"ABD AnyBody Can Draw"},{"name":"How to make a Onam pookalam","image":"https://i.ytimg.com/vi/9zKF8Dnf9sw/mqdefault.jpg","URL":"https://youtu.be/9zKF8Dnf9sw","youtubeID":"9zKF8Dnf9sw","source":"tim thankachan"},{"name":"Making Onappookkalam","image":"https://i.ytimg.com/vi/wsozvVUwa70/mqdefault.jpg","URL":"https://youtu.be/wsozvVUwa70","youtubeID":"wsozvVUwa70","source":"Deepa George"},{"name":"Make Flower Rangoli","image":"https://i.ytimg.com/vi/tp3wwLvQOTE/mqdefault.jpg","URL":"https://youtu.be/tp3wwLvQOTE","youtubeID":"tp3wwLvQOTE","source":"Cinecurry Lifestyle"},{"name":"flower rangoli designs","image":"https://i.ytimg.com/vi/QMs-RW7DbmA/mqdefault.jpg","URL":"https://youtu.be/QMs-RW7DbmA","youtubeID":"QMs-RW7DbmA","source":"Rangoli designs with colours // Arts and Crafts"}]